README.md
setup.py
rain_netbox_documents/__init__.py
rain_netbox_documents/forms.py
rain_netbox_documents/models.py
rain_netbox_documents/tables.py
rain_netbox_documents/urls.py
rain_netbox_documents/utils.py
rain_netbox_documents/views.py
rain_netbox_documents.egg-info/PKG-INFO
rain_netbox_documents.egg-info/SOURCES.txt
rain_netbox_documents.egg-info/dependency_links.txt
rain_netbox_documents.egg-info/not-zip-safe
rain_netbox_documents.egg-info/top_level.txt
rain_netbox_documents/migrations/0001_initial.py
rain_netbox_documents/migrations/__init__.py